XTBClient/__init__.py
XTBClient/client/__init__.py
XTBClient/client/axtb.py
XTBClient/client/xtb.py
XTBClient/errors.py
XTBClient/models/__init__.py
XTBClient/models/models.py
XTBClient/models/requests.py
XTBClient/xtb_base.py
xtbclient-0.1.2.dist-info/LICENSE
xtbclient-0.1.2.dist-info/METADATA
xtbclient-0.1.2.dist-info/WHEEL
xtbclient-0.1.2.dist-info/RECORD
