Metadata-Version: 2.1
Name: xtbclient
Version: 0.1.2
Summary: XTB trading platform client
License: MIT
Author: Cristian Libotean
Author-email: eblis102@gmail.com
Requires-Python: >=3.7,<4.0
Classifier: License :: OSI Approved :: MIT License
Classifier: Programming Language :: Python :: 3
Classifier: Programming Language :: Python :: 3.7
Classifier: Programming Language :: Python :: 3.8
Classifier: Programming Language :: Python :: 3.9
Classifier: Programming Language :: Python :: 3.10
Classifier: Programming Language :: Python :: 3.11
Requires-Dist: dataclasses-json (>=0.5.7,<0.6.0)
Requires-Dist: pytest-asyncio (>=0.18.3,<0.19.0)
Requires-Dist: pytest-mock (>=3.7.0,<4.0.0)
Requires-Dist: websocket-client (>=1.3.2,<2.0.0)
Requires-Dist: websockets (>=10.3,<11.0)
